transpara/__init__.py
transpara/logging_config.py
transpara/tlogging.py
transpara/tracing.py
transpara_py_sdk-0.20.0.dist-info/LICENSE.txt
transpara_py_sdk-0.20.0.dist-info/METADATA
transpara_py_sdk-0.20.0.dist-info/WHEEL
transpara_py_sdk-0.20.0.dist-info/top_level.txt
transpara_py_sdk-0.20.0.dist-info/RECORD
